longinus/__init__.py
longinus-1.1.dist-info/LICENSE
longinus-1.1.dist-info/METADATA
longinus-1.1.dist-info/WHEEL
longinus-1.1.dist-info/top_level.txt
longinus-1.1.dist-info/RECORD
