Metadata-Version: 2.1
Name: longinus
Version: 1.1
Summary: A experimental web crawler
Home-page: https://github.com/fatorius/Longinus
Author: Hugo Souza
Author-email: mail@hugosouza.com
License: UNKNOWN
Project-URL: Bug Tracker, https://github.com/fatorius/Longinus/issues
Platform: UNKNOWN
Classifier: Programming Language :: Python :: 3
Classifier: License :: OSI Approved :: MIT License
Classifier: Operating System :: OS Independent
Requires-Python: >=3.6
License-File: LICENSE
